{"_format":"","paths":{"artifacts":"out","build_infos":"out/build-info","sources":"src","tests":"test","scripts":"script","libraries":["lib"]},"files":{"lib/forge-std/src/Base.sol":{"lastModificationDate":1779515462861,"contentHash":"b30affbf365427e2","interfaceReprHash":null,"sourceName":"lib/forge-std/src/Base.sol","imports":["lib/forge-std/src/StdStorage.sol","lib/forge-std/src/Vm.sol"],"versionRequirement":">=0.6.2, <0.9.0","artifacts":{"CommonBase":{"0.8.30":{"default":{"path":"Base.sol\\CommonBase.json","build_id":"1d9fdadd1965c4b1"}}},"ScriptBase":{"0.8.30":{"default":{"path":"Base.sol\\ScriptBase.json","build_id":"1d9fdadd1965c4b1"}}},"TestBase":{"0.8.30":{"default":{"path":"Base.sol\\TestBase.json","build_id":"1d9fdadd1965c4b1"}}}},"seenByCompiler":true},"lib/forge-std/src/Script.sol":{"lastModificationDate":1779515462861,"contentHash":"654eb74437773a2d","interfaceReprHash":null,"sourceName":"lib/forge-std/src/Script.sol","imports":["lib/forge-std/src/Base.sol","lib/forge-std/src/StdChains.sol","lib/forge-std/src/StdCheats.sol","lib/forge-std/src/StdConstants.sol","lib/forge-std/src/StdJson.sol","lib/forge-std/src/StdMath.sol","lib/forge-std/src/StdStorage.sol","lib/forge-std/src/StdStyle.sol","lib/forge-std/src/StdUtils.sol","lib/forge-std/src/Vm.sol","lib/forge-std/src/console.sol","lib/forge-std/src/console2.sol","lib/forge-std/src/interfaces/IMulticall3.sol","lib/forge-std/src/safeconsole.sol"],"versionRequirement":">=0.6.2, <0.9.0","artifacts":{"Script":{"0.8.30":{"default":{"path":"Script.sol\\Script.json","build_id":"1d9fdadd1965c4b1"}}}},"seenByCompiler":true},"lib/forge-std/src/StdChains.sol":{"lastModificationDate":1779515462861,"contentHash":"a40952ce0d242817","interfaceReprHash":null,"sourceName":"lib/forge-std/src/StdChains.sol","imports":["lib/forge-std/src/Vm.sol"],"versionRequirement":">=0.6.2, <0.9.0","artifacts":{"StdChains":{"0.8.30":{"default":{"path":"StdChains.sol\\StdChains.json","build_id":"1d9fdadd1965c4b1"}}}},"seenByCompiler":true},"lib/forge-std/src/StdCheats.sol":{"lastModificationDate":1779515462861,"contentHash":"30325e8cda32c7ae","interfaceReprHash":null,"sourceName":"lib/forge-std/src/StdCheats.sol","imports":["lib/forge-std/src/StdStorage.sol","lib/forge-std/src/Vm.sol","lib/forge-std/src/console.sol","lib/forge-std/src/console2.sol"],"versionRequirement":">=0.6.2, <0.9.0","artifacts":{"StdCheats":{"0.8.30":{"default":{"path":"StdCheats.sol\\StdCheats.json","build_id":"1d9fdadd1965c4b1"}}},"StdCheatsSafe":{"0.8.30":{"default":{"path":"StdCheats.sol\\StdCheatsSafe.json","build_id":"1d9fdadd1965c4b1"}}}},"seenByCompiler":true},"lib/forge-std/src/StdConstants.sol":{"lastModificationDate":1779515462861,"contentHash":"23303eb7e922efe4","interfaceReprHash":null,"sourceName":"lib/forge-std/src/StdConstants.sol","imports":["lib/forge-std/src/Vm.sol","lib/forge-std/src/interfaces/IMulticall3.sol"],"versionRequirement":">=0.6.2, <0.9.0","artifacts":{"StdConstants":{"0.8.30":{"default":{"path":"StdConstants.sol\\StdConstants.json","build_id":"1d9fdadd1965c4b1"}}}},"seenByCompiler":true},"lib/forge-std/src/StdJson.sol":{"lastModificationDate":1779515462861,"contentHash":"5fb1b35c8fb281fd","interfaceReprHash":null,"sourceName":"lib/forge-std/src/StdJson.sol","imports":["lib/forge-std/src/Vm.sol"],"versionRequirement":">=0.6.0, <0.9.0","artifacts":{"stdJson":{"0.8.30":{"default":{"path":"StdJson.sol\\stdJson.json","build_id":"1d9fdadd1965c4b1"}}}},"seenByCompiler":true},"lib/forge-std/src/StdMath.sol":{"lastModificationDate":1779515462861,"contentHash":"72584abebada1e7a","interfaceReprHash":null,"sourceName":"lib/forge-std/src/StdMath.sol","imports":[],"versionRequirement":">=0.6.2, <0.9.0","artifacts":{"stdMath":{"0.8.30":{"default":{"path":"StdMath.sol\\stdMath.json","build_id":"1d9fdadd1965c4b1"}}}},"seenByCompiler":true},"lib/forge-std/src/StdStorage.sol":{"lastModificationDate":1779515462861,"contentHash":"9a44dcb9bda3bfa9","interfaceReprHash":null,"sourceName":"lib/forge-std/src/StdStorage.sol","imports":["lib/forge-std/src/Vm.sol"],"versionRequirement":">=0.6.2, <0.9.0","artifacts":{"stdStorage":{"0.8.30":{"default":{"path":"StdStorage.sol\\stdStorage.json","build_id":"1d9fdadd1965c4b1"}}},"stdStorageSafe":{"0.8.30":{"default":{"path":"StdStorage.sol\\stdStorageSafe.json","build_id":"1d9fdadd1965c4b1"}}}},"seenByCompiler":true},"lib/forge-std/src/StdStyle.sol":{"lastModificationDate":1779515462861,"contentHash":"ee166ef95092736e","interfaceReprHash":null,"sourceName":"lib/forge-std/src/StdStyle.sol","imports":["lib/forge-std/src/Vm.sol"],"versionRequirement":">=0.4.22, <0.9.0","artifacts":{"StdStyle":{"0.8.30":{"default":{"path":"StdStyle.sol\\StdStyle.json","build_id":"1d9fdadd1965c4b1"}}}},"seenByCompiler":true},"lib/forge-std/src/StdUtils.sol":{"lastModificationDate":1779515462878,"contentHash":"b7cdeb66252de708","interfaceReprHash":null,"sourceName":"lib/forge-std/src/StdUtils.sol","imports":["lib/forge-std/src/Vm.sol","lib/forge-std/src/interfaces/IMulticall3.sol"],"versionRequirement":">=0.6.2, <0.9.0","artifacts":{"StdUtils":{"0.8.30":{"default":{"path":"StdUtils.sol\\StdUtils.json","build_id":"1d9fdadd1965c4b1"}}}},"seenByCompiler":true},"lib/forge-std/src/Vm.sol":{"lastModificationDate":1779515462878,"contentHash":"e42237c90542cb12","interfaceReprHash":null,"sourceName":"lib/forge-std/src/Vm.sol","imports":[],"versionRequirement":">=0.6.2, <0.9.0","artifacts":{"Vm":{"0.8.30":{"default":{"path":"Vm.sol\\Vm.json","build_id":"1d9fdadd1965c4b1"}}},"VmSafe":{"0.8.30":{"default":{"path":"Vm.sol\\VmSafe.json","build_id":"1d9fdadd1965c4b1"}}}},"seenByCompiler":true},"lib/forge-std/src/console.sol":{"lastModificationDate":1779515462878,"contentHash":"bae85493a76fb054","interfaceReprHash":null,"sourceName":"lib/forge-std/src/console.sol","imports":[],"versionRequirement":">=0.4.22, <0.9.0","artifacts":{"console":{"0.8.30":{"default":{"path":"console.sol\\console.json","build_id":"1d9fdadd1965c4b1"}}}},"seenByCompiler":true},"lib/forge-std/src/console2.sol":{"lastModificationDate":1779515462878,"contentHash":"49a7da3dfc404603","interfaceReprHash":null,"sourceName":"lib/forge-std/src/console2.sol","imports":["lib/forge-std/src/console.sol"],"versionRequirement":">=0.4.22, <0.9.0","artifacts":{},"seenByCompiler":true},"lib/forge-std/src/interfaces/IMulticall3.sol":{"lastModificationDate":1779515462878,"contentHash":"b680a332ebf10901","interfaceReprHash":null,"sourceName":"lib/forge-std/src/interfaces/IMulticall3.sol","imports":[],"versionRequirement":">=0.6.2, <0.9.0","artifacts":{"IMulticall3":{"0.8.30":{"default":{"path":"IMulticall3.sol\\IMulticall3.json","build_id":"1d9fdadd1965c4b1"}}}},"seenByCompiler":true},"lib/forge-std/src/safeconsole.sol":{"lastModificationDate":1779515462878,"contentHash":"621653b34a6691ea","interfaceReprHash":null,"sourceName":"lib/forge-std/src/safeconsole.sol","imports":[],"versionRequirement":">=0.6.2, <0.9.0","artifacts":{"safeconsole":{"0.8.30":{"default":{"path":"safeconsole.sol\\safeconsole.json","build_id":"1d9fdadd1965c4b1"}}}},"seenByCompiler":true},"lib/uniswap-hooks/lib/v4-core/lib/openzeppelin-contracts/contracts/token/ERC20/IERC20.sol":{"lastModificationDate":1779515608259,"contentHash":"f60cdd96fb4cd69a","interfaceReprHash":null,"sourceName":"lib/uniswap-hooks/lib/v4-core/lib/openzeppelin-contracts/contracts/token/ERC20/IERC20.sol","imports":[],"versionRequirement":"^0.8.20","artifacts":{"IERC20":{"0.8.30":{"default":{"path":"IERC20.sol\\IERC20.json","build_id":"1d9fdadd1965c4b1"}}}},"seenByCompiler":true},"lib/uniswap-hooks/lib/v4-core/src/interfaces/IExtsload.sol":{"lastModificationDate":1779515563959,"contentHash":"a17834d80eb9b2bc","interfaceReprHash":null,"sourceName":"lib/uniswap-hooks/lib/v4-core/src/interfaces/IExtsload.sol","imports":[],"versionRequirement":"^0.8.0","artifacts":{"IExtsload":{"0.8.30":{"default":{"path":"IExtsload.sol\\IExtsload.json","build_id":"1d9fdadd1965c4b1"}}}},"seenByCompiler":true},"lib/uniswap-hooks/lib/v4-core/src/interfaces/IExttload.sol":{"lastModificationDate":1779515563959,"contentHash":"2190199c75e2ba4c","interfaceReprHash":null,"sourceName":"lib/uniswap-hooks/lib/v4-core/src/interfaces/IExttload.sol","imports":[],"versionRequirement":"^0.8.24","artifacts":{"IExttload":{"0.8.30":{"default":{"path":"IExttload.sol\\IExttload.json","build_id":"1d9fdadd1965c4b1"}}}},"seenByCompiler":true},"lib/uniswap-hooks/lib/v4-core/src/interfaces/IHooks.sol":{"lastModificationDate":1779515563959,"contentHash":"20955fcb07703cbb","interfaceReprHash":null,"sourceName":"lib/uniswap-hooks/lib/v4-core/src/interfaces/IHooks.sol","imports":["lib/uniswap-hooks/lib/v4-core\\src/interfaces/IHooks.sol","lib/uniswap-hooks/lib/v4-core/src/interfaces/external/IERC20Minimal.sol","lib/uniswap-hooks/lib/v4-core/src/libraries/CustomRevert.sol","lib/uniswap-hooks/lib/v4-core/src/libraries/SafeCast.sol","lib/uniswap-hooks/lib/v4-core\\src/types/BalanceDelta.sol","lib/uniswap-hooks/lib/v4-core\\src/types/BeforeSwapDelta.sol","lib/uniswap-hooks/lib/v4-core\\src/types/Currency.sol","lib/uniswap-hooks/lib/v4-core\\src/types/PoolId.sol","lib/uniswap-hooks/lib/v4-core\\src/types/PoolKey.sol","lib/uniswap-hooks/lib/v4-core\\src/types/PoolOperation.sol"],"versionRequirement":"^0.8.0","artifacts":{"IHooks":{"0.8.30":{"default":{"path":"IHooks.sol\\IHooks.json","build_id":"1d9fdadd1965c4b1"}}}},"seenByCompiler":true},"lib/uniswap-hooks/lib/v4-core/src/interfaces/IPoolManager.sol":{"lastModificationDate":1779515563959,"contentHash":"55b387e0bef6194d","interfaceReprHash":null,"sourceName":"lib/uniswap-hooks/lib/v4-core/src/interfaces/IPoolManager.sol","imports":["lib/uniswap-hooks/lib/v4-core/src/interfaces/IExtsload.sol","lib/uniswap-hooks/lib/v4-core/src/interfaces/IExttload.sol","lib/uniswap-hooks/lib/v4-core\\src/interfaces/IHooks.sol","lib/uniswap-hooks/lib/v4-core/src/interfaces/IProtocolFees.sol","lib/uniswap-hooks/lib/v4-core/src/interfaces/external/IERC20Minimal.sol","lib/uniswap-hooks/lib/v4-core/src/interfaces/external/IERC6909Claims.sol","lib/uniswap-hooks/lib/v4-core/src/libraries/CustomRevert.sol","lib/uniswap-hooks/lib/v4-core/src/libraries/SafeCast.sol","lib/uniswap-hooks/lib/v4-core\\src/types/BalanceDelta.sol","lib/uniswap-hooks/lib/v4-core\\src/types/BeforeSwapDelta.sol","lib/uniswap-hooks/lib/v4-core\\src/types/Currency.sol","lib/uniswap-hooks/lib/v4-core\\src/types/PoolId.sol","lib/uniswap-hooks/lib/v4-core\\src/types/PoolKey.sol","lib/uniswap-hooks/lib/v4-core\\src/types/PoolOperation.sol"],"versionRequirement":"^0.8.24","artifacts":{"IPoolManager":{"0.8.30":{"default":{"path":"IPoolManager.sol\\IPoolManager.json","build_id":"1d9fdadd1965c4b1"}}}},"seenByCompiler":true},"lib/uniswap-hooks/lib/v4-core/src/interfaces/IProtocolFees.sol":{"lastModificationDate":1779515563959,"contentHash":"3c0177865aba04df","interfaceReprHash":null,"sourceName":"lib/uniswap-hooks/lib/v4-core/src/interfaces/IProtocolFees.sol","imports":["lib/uniswap-hooks/lib/v4-core\\src/interfaces/IHooks.sol","lib/uniswap-hooks/lib/v4-core/src/interfaces/external/IERC20Minimal.sol","lib/uniswap-hooks/lib/v4-core/src/libraries/CustomRevert.sol","lib/uniswap-hooks/lib/v4-core/src/libraries/SafeCast.sol","lib/uniswap-hooks/lib/v4-core\\src/types/BalanceDelta.sol","lib/uniswap-hooks/lib/v4-core\\src/types/BeforeSwapDelta.sol","lib/uniswap-hooks/lib/v4-core\\src/types/Currency.sol","lib/uniswap-hooks/lib/v4-core\\src/types/PoolId.sol","lib/uniswap-hooks/lib/v4-core\\src/types/PoolKey.sol","lib/uniswap-hooks/lib/v4-core\\src/types/PoolOperation.sol"],"versionRequirement":"^0.8.0","artifacts":{"IProtocolFees":{"0.8.30":{"default":{"path":"IProtocolFees.sol\\IProtocolFees.json","build_id":"1d9fdadd1965c4b1"}}}},"seenByCompiler":true},"lib/uniswap-hooks/lib/v4-core/src/interfaces/callback/IUnlockCallback.sol":{"lastModificationDate":1779515563959,"contentHash":"34c17f6eb3fe1724","interfaceReprHash":null,"sourceName":"lib/uniswap-hooks/lib/v4-core/src/interfaces/callback/IUnlockCallback.sol","imports":[],"versionRequirement":"^0.8.0","artifacts":{"IUnlockCallback":{"0.8.30":{"default":{"path":"IUnlockCallback.sol\\IUnlockCallback.json","build_id":"1d9fdadd1965c4b1"}}}},"seenByCompiler":true},"lib/uniswap-hooks/lib/v4-core/src/interfaces/external/IERC20Minimal.sol":{"lastModificationDate":1779515563959,"contentHash":"0f6d7a7184d7615a","interfaceReprHash":null,"sourceName":"lib/uniswap-hooks/lib/v4-core/src/interfaces/external/IERC20Minimal.sol","imports":[],"versionRequirement":"^0.8.0","artifacts":{"IERC20Minimal":{"0.8.30":{"default":{"path":"IERC20Minimal.sol\\IERC20Minimal.json","build_id":"1d9fdadd1965c4b1"}}}},"seenByCompiler":true},"lib/uniswap-hooks/lib/v4-core/src/interfaces/external/IERC6909Claims.sol":{"lastModificationDate":1779515563959,"contentHash":"569c1f335115f451","interfaceReprHash":null,"sourceName":"lib/uniswap-hooks/lib/v4-core/src/interfaces/external/IERC6909Claims.sol","imports":[],"versionRequirement":"^0.8.0","artifacts":{"IERC6909Claims":{"0.8.30":{"default":{"path":"IERC6909Claims.sol\\IERC6909Claims.json","build_id":"1d9fdadd1965c4b1"}}}},"seenByCompiler":true},"lib/uniswap-hooks/lib/v4-core/src/libraries/BitMath.sol":{"lastModificationDate":1779515563959,"contentHash":"aafc86b627d37351","interfaceReprHash":null,"sourceName":"lib/uniswap-hooks/lib/v4-core/src/libraries/BitMath.sol","imports":[],"versionRequirement":"^0.8.0","artifacts":{"BitMath":{"0.8.30":{"default":{"path":"BitMath.sol\\BitMath.json","build_id":"1d9fdadd1965c4b1"}}}},"seenByCompiler":true},"lib/uniswap-hooks/lib/v4-core/src/libraries/CustomRevert.sol":{"lastModificationDate":1779515563959,"contentHash":"ecf219a3788afb76","interfaceReprHash":null,"sourceName":"lib/uniswap-hooks/lib/v4-core/src/libraries/CustomRevert.sol","imports":[],"versionRequirement":"^0.8.0","artifacts":{"CustomRevert":{"0.8.30":{"default":{"path":"CustomRevert.sol\\CustomRevert.json","build_id":"1d9fdadd1965c4b1"}}}},"seenByCompiler":true},"lib/uniswap-hooks/lib/v4-core/src/libraries/Hooks.sol":{"lastModificationDate":1779515563959,"contentHash":"f6cd8f149da64118","interfaceReprHash":null,"sourceName":"lib/uniswap-hooks/lib/v4-core/src/libraries/Hooks.sol","imports":["lib/uniswap-hooks/lib/v4-core/src/interfaces/IExtsload.sol","lib/uniswap-hooks/lib/v4-core/src/interfaces/IExttload.sol","lib/uniswap-hooks/lib/v4-core\\src/interfaces/IHooks.sol","lib/uniswap-hooks/lib/v4-core\\src/interfaces/IPoolManager.sol","lib/uniswap-hooks/lib/v4-core/src/interfaces/IProtocolFees.sol","lib/uniswap-hooks/lib/v4-core/src/interfaces/external/IERC20Minimal.sol","lib/uniswap-hooks/lib/v4-core/src/interfaces/external/IERC6909Claims.sol","lib/uniswap-hooks/lib/v4-core/src/libraries/CustomRevert.sol","lib/uniswap-hooks/lib/v4-core/src/libraries/LPFeeLibrary.sol","lib/uniswap-hooks/lib/v4-core/src/libraries/ParseBytes.sol","lib/uniswap-hooks/lib/v4-core/src/libraries/SafeCast.sol","lib/uniswap-hooks/lib/v4-core\\src/types/BalanceDelta.sol","lib/uniswap-hooks/lib/v4-core\\src/types/BeforeSwapDelta.sol","lib/uniswap-hooks/lib/v4-core\\src/types/Currency.sol","lib/uniswap-hooks/lib/v4-core\\src/types/PoolId.sol","lib/uniswap-hooks/lib/v4-core\\src/types/PoolKey.sol","lib/uniswap-hooks/lib/v4-core\\src/types/PoolOperation.sol"],"versionRequirement":"^0.8.0","artifacts":{"Hooks":{"0.8.30":{"default":{"path":"Hooks.sol\\Hooks.json","build_id":"1d9fdadd1965c4b1"}}}},"seenByCompiler":true},"lib/uniswap-hooks/lib/v4-core/src/libraries/LPFeeLibrary.sol":{"lastModificationDate":1779515563959,"contentHash":"9e0465899850be20","interfaceReprHash":null,"sourceName":"lib/uniswap-hooks/lib/v4-core/src/libraries/LPFeeLibrary.sol","imports":["lib/uniswap-hooks/lib/v4-core/src/libraries/CustomRevert.sol"],"versionRequirement":"^0.8.0","artifacts":{"LPFeeLibrary":{"0.8.30":{"default":{"path":"LPFeeLibrary.sol\\LPFeeLibrary.json","build_id":"1d9fdadd1965c4b1"}}}},"seenByCompiler":true},"lib/uniswap-hooks/lib/v4-core/src/libraries/ParseBytes.sol":{"lastModificationDate":1779515563959,"contentHash":"006aefe2d924bee9","interfaceReprHash":null,"sourceName":"lib/uniswap-hooks/lib/v4-core/src/libraries/ParseBytes.sol","imports":[],"versionRequirement":"^0.8.0","artifacts":{"ParseBytes":{"0.8.30":{"default":{"path":"ParseBytes.sol\\ParseBytes.json","build_id":"1d9fdadd1965c4b1"}}}},"seenByCompiler":true},"lib/uniswap-hooks/lib/v4-core/src/libraries/SafeCast.sol":{"lastModificationDate":1779515563959,"contentHash":"26fb30c1b1acd84b","interfaceReprHash":null,"sourceName":"lib/uniswap-hooks/lib/v4-core/src/libraries/SafeCast.sol","imports":["lib/uniswap-hooks/lib/v4-core/src/libraries/CustomRevert.sol"],"versionRequirement":"^0.8.0","artifacts":{"SafeCast":{"0.8.30":{"default":{"path":"SafeCast.sol\\SafeCast.json","build_id":"1d9fdadd1965c4b1"}}}},"seenByCompiler":true},"lib/uniswap-hooks/lib/v4-core/src/libraries/TickMath.sol":{"lastModificationDate":1779515563975,"contentHash":"1b639507c250adc8","interfaceReprHash":null,"sourceName":"lib/uniswap-hooks/lib/v4-core/src/libraries/TickMath.sol","imports":["lib/uniswap-hooks/lib/v4-core/src/libraries/BitMath.sol","lib/uniswap-hooks/lib/v4-core/src/libraries/CustomRevert.sol"],"versionRequirement":"^0.8.0","artifacts":{"TickMath":{"0.8.30":{"default":{"path":"TickMath.sol\\TickMath.json","build_id":"1d9fdadd1965c4b1"}}}},"seenByCompiler":true},"lib/uniswap-hooks/lib/v4-core/src/types/BalanceDelta.sol":{"lastModificationDate":1779515563975,"contentHash":"07b92dc9ccfa0d15","interfaceReprHash":null,"sourceName":"lib/uniswap-hooks/lib/v4-core/src/types/BalanceDelta.sol","imports":["lib/uniswap-hooks/lib/v4-core/src/libraries/CustomRevert.sol","lib/uniswap-hooks/lib/v4-core/src/libraries/SafeCast.sol"],"versionRequirement":"^0.8.0","artifacts":{"BalanceDeltaLibrary":{"0.8.30":{"default":{"path":"BalanceDelta.sol\\BalanceDeltaLibrary.json","build_id":"1d9fdadd1965c4b1"}}}},"seenByCompiler":true},"lib/uniswap-hooks/lib/v4-core/src/types/BeforeSwapDelta.sol":{"lastModificationDate":1779515563975,"contentHash":"b33ea5fde5fb62e8","interfaceReprHash":null,"sourceName":"lib/uniswap-hooks/lib/v4-core/src/types/BeforeSwapDelta.sol","imports":[],"versionRequirement":"^0.8.0","artifacts":{"BeforeSwapDeltaLibrary":{"0.8.30":{"default":{"path":"BeforeSwapDelta.sol\\BeforeSwapDeltaLibrary.json","build_id":"1d9fdadd1965c4b1"}}}},"seenByCompiler":true},"lib/uniswap-hooks/lib/v4-core/src/types/Currency.sol":{"lastModificationDate":1779515563975,"contentHash":"3d6032f443b702df","interfaceReprHash":null,"sourceName":"lib/uniswap-hooks/lib/v4-core/src/types/Currency.sol","imports":["lib/uniswap-hooks/lib/v4-core/src/interfaces/external/IERC20Minimal.sol","lib/uniswap-hooks/lib/v4-core/src/libraries/CustomRevert.sol"],"versionRequirement":"^0.8.0","artifacts":{"CurrencyLibrary":{"0.8.30":{"default":{"path":"Currency.sol\\CurrencyLibrary.json","build_id":"1d9fdadd1965c4b1"}}}},"seenByCompiler":true},"lib/uniswap-hooks/lib/v4-core/src/types/PoolId.sol":{"lastModificationDate":1779515563991,"contentHash":"cc46093270e207ad","interfaceReprHash":null,"sourceName":"lib/uniswap-hooks/lib/v4-core/src/types/PoolId.sol","imports":["lib/uniswap-hooks/lib/v4-core\\src/interfaces/IHooks.sol","lib/uniswap-hooks/lib/v4-core/src/interfaces/external/IERC20Minimal.sol","lib/uniswap-hooks/lib/v4-core/src/libraries/CustomRevert.sol","lib/uniswap-hooks/lib/v4-core/src/libraries/SafeCast.sol","lib/uniswap-hooks/lib/v4-core\\src/types/BalanceDelta.sol","lib/uniswap-hooks/lib/v4-core\\src/types/BeforeSwapDelta.sol","lib/uniswap-hooks/lib/v4-core\\src/types/Currency.sol","lib/uniswap-hooks/lib/v4-core\\src/types/PoolId.sol","lib/uniswap-hooks/lib/v4-core\\src/types/PoolKey.sol","lib/uniswap-hooks/lib/v4-core\\src/types/PoolOperation.sol"],"versionRequirement":"^0.8.0","artifacts":{"PoolIdLibrary":{"0.8.30":{"default":{"path":"PoolId.sol\\PoolIdLibrary.json","build_id":"1d9fdadd1965c4b1"}}}},"seenByCompiler":true},"lib/uniswap-hooks/lib/v4-core/src/types/PoolKey.sol":{"lastModificationDate":1779515563991,"contentHash":"ade39c50c30272fb","interfaceReprHash":null,"sourceName":"lib/uniswap-hooks/lib/v4-core/src/types/PoolKey.sol","imports":["lib/uniswap-hooks/lib/v4-core\\src/interfaces/IHooks.sol","lib/uniswap-hooks/lib/v4-core/src/interfaces/external/IERC20Minimal.sol","lib/uniswap-hooks/lib/v4-core/src/libraries/CustomRevert.sol","lib/uniswap-hooks/lib/v4-core/src/libraries/SafeCast.sol","lib/uniswap-hooks/lib/v4-core\\src/types/BalanceDelta.sol","lib/uniswap-hooks/lib/v4-core\\src/types/BeforeSwapDelta.sol","lib/uniswap-hooks/lib/v4-core\\src/types/Currency.sol","lib/uniswap-hooks/lib/v4-core\\src/types/PoolId.sol","lib/uniswap-hooks/lib/v4-core\\src/types/PoolKey.sol","lib/uniswap-hooks/lib/v4-core\\src/types/PoolOperation.sol"],"versionRequirement":"^0.8.0","artifacts":{},"seenByCompiler":true},"lib/uniswap-hooks/lib/v4-core/src/types/PoolOperation.sol":{"lastModificationDate":1779515563991,"contentHash":"88f097de43481c6e","interfaceReprHash":null,"sourceName":"lib/uniswap-hooks/lib/v4-core/src/types/PoolOperation.sol","imports":["lib/uniswap-hooks/lib/v4-core\\src/interfaces/IHooks.sol","lib/uniswap-hooks/lib/v4-core/src/interfaces/external/IERC20Minimal.sol","lib/uniswap-hooks/lib/v4-core/src/libraries/CustomRevert.sol","lib/uniswap-hooks/lib/v4-core/src/libraries/SafeCast.sol","lib/uniswap-hooks/lib/v4-core\\src/types/BalanceDelta.sol","lib/uniswap-hooks/lib/v4-core\\src/types/BeforeSwapDelta.sol","lib/uniswap-hooks/lib/v4-core\\src/types/Currency.sol","lib/uniswap-hooks/lib/v4-core\\src/types/PoolId.sol","lib/uniswap-hooks/lib/v4-core\\src/types/PoolKey.sol","lib/uniswap-hooks/lib/v4-core\\src/types/PoolOperation.sol"],"versionRequirement":"^0.8.24","artifacts":{},"seenByCompiler":true},"lib/uniswap-hooks/lib/v4-periphery/src/utils/HookMiner.sol":{"lastModificationDate":1779515614929,"contentHash":"2c9ef4aab5559655","interfaceReprHash":null,"sourceName":"lib/uniswap-hooks/lib/v4-periphery/src/utils/HookMiner.sol","imports":["lib/uniswap-hooks/lib/v4-core/src/interfaces/IExtsload.sol","lib/uniswap-hooks/lib/v4-core/src/interfaces/IExttload.sol","lib/uniswap-hooks/lib/v4-core/src/interfaces/IHooks.sol","lib/uniswap-hooks/lib/v4-core\\src/interfaces/IPoolManager.sol","lib/uniswap-hooks/lib/v4-core/src/interfaces/IProtocolFees.sol","lib/uniswap-hooks/lib/v4-core/src/interfaces/external/IERC20Minimal.sol","lib/uniswap-hooks/lib/v4-core/src/interfaces/external/IERC6909Claims.sol","lib/uniswap-hooks/lib/v4-core/src/libraries/CustomRevert.sol","lib/uniswap-hooks/lib/v4-core\\src/libraries/Hooks.sol","lib/uniswap-hooks/lib/v4-core/src/libraries/LPFeeLibrary.sol","lib/uniswap-hooks/lib/v4-core/src/libraries/ParseBytes.sol","lib/uniswap-hooks/lib/v4-core/src/libraries/SafeCast.sol","lib/uniswap-hooks/lib/v4-core\\src/types/BalanceDelta.sol","lib/uniswap-hooks/lib/v4-core\\src/types/BeforeSwapDelta.sol","lib/uniswap-hooks/lib/v4-core/src/types/Currency.sol","lib/uniswap-hooks/lib/v4-core\\src/types/PoolId.sol","lib/uniswap-hooks/lib/v4-core\\src/types/PoolKey.sol","lib/uniswap-hooks/lib/v4-core/src/types/PoolOperation.sol"],"versionRequirement":"^0.8.21","artifacts":{"HookMiner":{"0.8.30":{"default":{"path":"HookMiner.sol\\HookMiner.json","build_id":"a5ea3ad17e6a735e"}}}},"seenByCompiler":true},"lib/uniswap-hooks/src/base/BaseHook.sol":{"lastModificationDate":1779515463193,"contentHash":"da27fab03ceaaa50","interfaceReprHash":null,"sourceName":"lib/uniswap-hooks/src/base/BaseHook.sol","imports":["lib/uniswap-hooks/lib/v4-core/src/interfaces/IExtsload.sol","lib/uniswap-hooks/lib/v4-core/src/interfaces/IExttload.sol","lib/uniswap-hooks/lib/v4-core\\src/interfaces/IHooks.sol","lib/uniswap-hooks/lib/v4-core\\src/interfaces/IPoolManager.sol","lib/uniswap-hooks/lib/v4-core/src/interfaces/IProtocolFees.sol","lib/uniswap-hooks/lib/v4-core/src/interfaces/external/IERC20Minimal.sol","lib/uniswap-hooks/lib/v4-core/src/interfaces/external/IERC6909Claims.sol","lib/uniswap-hooks/lib/v4-core/src/libraries/CustomRevert.sol","lib/uniswap-hooks/lib/v4-core\\src/libraries/Hooks.sol","lib/uniswap-hooks/lib/v4-core/src/libraries/LPFeeLibrary.sol","lib/uniswap-hooks/lib/v4-core/src/libraries/ParseBytes.sol","lib/uniswap-hooks/lib/v4-core/src/libraries/SafeCast.sol","lib/uniswap-hooks/lib/v4-core\\src/types/BalanceDelta.sol","lib/uniswap-hooks/lib/v4-core\\src/types/BeforeSwapDelta.sol","lib/uniswap-hooks/lib/v4-core\\src/types/Currency.sol","lib/uniswap-hooks/lib/v4-core\\src/types/PoolId.sol","lib/uniswap-hooks/lib/v4-core\\src/types/PoolKey.sol","lib/uniswap-hooks/lib/v4-core\\src/types/PoolOperation.sol"],"versionRequirement":"^0.8.24","artifacts":{"BaseHook":{"0.8.30":{"default":{"path":"BaseHook.sol\\BaseHook.json","build_id":"1d9fdadd1965c4b1"}}}},"seenByCompiler":true},"script/DeployHook.s.sol":{"lastModificationDate":1779601249536,"contentHash":"e361fb8c9747a92c","interfaceReprHash":null,"sourceName":"script/DeployHook.s.sol","imports":["lib/forge-std/src/Base.sol","lib/forge-std/src\\Script.sol","lib/forge-std/src/StdChains.sol","lib/forge-std/src/StdCheats.sol","lib/forge-std/src/StdConstants.sol","lib/forge-std/src/StdJson.sol","lib/forge-std/src/StdMath.sol","lib/forge-std/src/StdStorage.sol","lib/forge-std/src/StdStyle.sol","lib/forge-std/src/StdUtils.sol","lib/forge-std/src/Vm.sol","lib/forge-std/src/console.sol","lib/forge-std/src/console2.sol","lib/forge-std/src/interfaces/IMulticall3.sol","lib/forge-std/src/safeconsole.sol","lib/uniswap-hooks/lib/v4-core/src/interfaces/IExtsload.sol","lib/uniswap-hooks/lib/v4-core/src/interfaces/IExttload.sol","lib/uniswap-hooks/lib/v4-core/src/interfaces/IHooks.sol","lib/uniswap-hooks/lib/v4-core\\src/interfaces/IPoolManager.sol","lib/uniswap-hooks/lib/v4-core/src/interfaces/IProtocolFees.sol","lib/uniswap-hooks/lib/v4-core/src/interfaces/external/IERC20Minimal.sol","lib/uniswap-hooks/lib/v4-core/src/interfaces/external/IERC6909Claims.sol","lib/uniswap-hooks/lib/v4-core/src/libraries/CustomRevert.sol","lib/uniswap-hooks/lib/v4-core\\src/libraries/Hooks.sol","lib/uniswap-hooks/lib/v4-core/src/libraries/LPFeeLibrary.sol","lib/uniswap-hooks/lib/v4-core/src/libraries/ParseBytes.sol","lib/uniswap-hooks/lib/v4-core/src/libraries/SafeCast.sol","lib/uniswap-hooks/lib/v4-core\\src/types/BalanceDelta.sol","lib/uniswap-hooks/lib/v4-core\\src/types/BeforeSwapDelta.sol","lib/uniswap-hooks/lib/v4-core/src/types/Currency.sol","lib/uniswap-hooks/lib/v4-core\\src/types/PoolId.sol","lib/uniswap-hooks/lib/v4-core\\src/types/PoolKey.sol","lib/uniswap-hooks/lib/v4-core/src/types/PoolOperation.sol","lib/uniswap-hooks/lib/v4-periphery\\src/utils/HookMiner.sol","lib/uniswap-hooks\\src/base/BaseHook.sol","src\\AaveHealthHook.sol","src\\interfaces\\IAavePool.sol"],"versionRequirement":"^0.8.26","artifacts":{"DeployHook":{"0.8.30":{"default":{"path":"DeployHook.s.sol\\DeployHook.json","build_id":"c3958264cc353a87"}}}},"seenByCompiler":true},"script/ExecuteSwap.s.sol":{"lastModificationDate":1779602185646,"contentHash":"c4bebc6b47e48b16","interfaceReprHash":null,"sourceName":"script/ExecuteSwap.s.sol","imports":["lib/forge-std/src/Base.sol","lib/forge-std/src\\Script.sol","lib/forge-std/src/StdChains.sol","lib/forge-std/src/StdCheats.sol","lib/forge-std/src/StdConstants.sol","lib/forge-std/src/StdJson.sol","lib/forge-std/src/StdMath.sol","lib/forge-std/src/StdStorage.sol","lib/forge-std/src/StdStyle.sol","lib/forge-std/src/StdUtils.sol","lib/forge-std/src/Vm.sol","lib/forge-std/src/console.sol","lib/forge-std/src/console2.sol","lib/forge-std/src/interfaces/IMulticall3.sol","lib/forge-std/src/safeconsole.sol","lib/uniswap-hooks/lib/v4-core/lib/openzeppelin-contracts/contracts\\token/ERC20/IERC20.sol","lib/uniswap-hooks/lib/v4-core/src/interfaces/IExtsload.sol","lib/uniswap-hooks/lib/v4-core/src/interfaces/IExttload.sol","lib/uniswap-hooks/lib/v4-core\\src/interfaces/IHooks.sol","lib/uniswap-hooks/lib/v4-core\\src/interfaces/IPoolManager.sol","lib/uniswap-hooks/lib/v4-core/src/interfaces/IProtocolFees.sol","lib/uniswap-hooks/lib/v4-core\\src/interfaces/callback/IUnlockCallback.sol","lib/uniswap-hooks/lib/v4-core/src/interfaces/external/IERC20Minimal.sol","lib/uniswap-hooks/lib/v4-core/src/interfaces/external/IERC6909Claims.sol","lib/uniswap-hooks/lib/v4-core/src/libraries/BitMath.sol","lib/uniswap-hooks/lib/v4-core/src/libraries/CustomRevert.sol","lib/uniswap-hooks/lib/v4-core/src/libraries/SafeCast.sol","lib/uniswap-hooks/lib/v4-core\\src/libraries/TickMath.sol","lib/uniswap-hooks/lib/v4-core\\src/types/BalanceDelta.sol","lib/uniswap-hooks/lib/v4-core\\src/types/BeforeSwapDelta.sol","lib/uniswap-hooks/lib/v4-core\\src/types/Currency.sol","lib/uniswap-hooks/lib/v4-core\\src/types/PoolId.sol","lib/uniswap-hooks/lib/v4-core\\src/types/PoolKey.sol","lib/uniswap-hooks/lib/v4-core\\src/types/PoolOperation.sol"],"versionRequirement":"^0.8.26","artifacts":{"ExecuteSwap":{"0.8.30":{"default":{"path":"ExecuteSwap.s.sol\\ExecuteSwap.json","build_id":"1d5d08d4361a8553"}}},"SwapHelper":{"0.8.30":{"default":{"path":"ExecuteSwap.s.sol\\SwapHelper.json","build_id":"1d5d08d4361a8553"}}}},"seenByCompiler":true},"script/InitializePool.s.sol":{"lastModificationDate":1779601259719,"contentHash":"73bfb26346a12f74","interfaceReprHash":null,"sourceName":"script/InitializePool.s.sol","imports":["lib/forge-std/src/Base.sol","lib/forge-std/src\\Script.sol","lib/forge-std/src/StdChains.sol","lib/forge-std/src/StdCheats.sol","lib/forge-std/src/StdConstants.sol","lib/forge-std/src/StdJson.sol","lib/forge-std/src/StdMath.sol","lib/forge-std/src/StdStorage.sol","lib/forge-std/src/StdStyle.sol","lib/forge-std/src/StdUtils.sol","lib/forge-std/src/Vm.sol","lib/forge-std/src/console.sol","lib/forge-std/src/console2.sol","lib/forge-std/src/interfaces/IMulticall3.sol","lib/forge-std/src/safeconsole.sol","lib/uniswap-hooks/lib/v4-core/lib/openzeppelin-contracts/contracts\\token/ERC20/IERC20.sol","lib/uniswap-hooks/lib/v4-core/src/interfaces/IExtsload.sol","lib/uniswap-hooks/lib/v4-core/src/interfaces/IExttload.sol","lib/uniswap-hooks/lib/v4-core\\src/interfaces/IHooks.sol","lib/uniswap-hooks/lib/v4-core\\src/interfaces/IPoolManager.sol","lib/uniswap-hooks/lib/v4-core/src/interfaces/IProtocolFees.sol","lib/uniswap-hooks/lib/v4-core\\src/interfaces/callback/IUnlockCallback.sol","lib/uniswap-hooks/lib/v4-core/src/interfaces/external/IERC20Minimal.sol","lib/uniswap-hooks/lib/v4-core/src/interfaces/external/IERC6909Claims.sol","lib/uniswap-hooks/lib/v4-core/src/libraries/BitMath.sol","lib/uniswap-hooks/lib/v4-core/src/libraries/CustomRevert.sol","lib/uniswap-hooks/lib/v4-core/src/libraries/SafeCast.sol","lib/uniswap-hooks/lib/v4-core\\src/libraries/TickMath.sol","lib/uniswap-hooks/lib/v4-core\\src/types/BalanceDelta.sol","lib/uniswap-hooks/lib/v4-core\\src/types/BeforeSwapDelta.sol","lib/uniswap-hooks/lib/v4-core\\src/types/Currency.sol","lib/uniswap-hooks/lib/v4-core\\src/types/PoolId.sol","lib/uniswap-hooks/lib/v4-core\\src/types/PoolKey.sol","lib/uniswap-hooks/lib/v4-core\\src/types/PoolOperation.sol"],"versionRequirement":"^0.8.26","artifacts":{"InitializePool":{"0.8.30":{"default":{"path":"InitializePool.s.sol\\InitializePool.json","build_id":"036c2ce3fcb75bac"}}},"LiquidityHelper":{"0.8.30":{"default":{"path":"InitializePool.s.sol\\LiquidityHelper.json","build_id":"036c2ce3fcb75bac"}}}},"seenByCompiler":true},"src/AaveHealthHook.sol":{"lastModificationDate":1779602286680,"contentHash":"51492963c4141f0e","interfaceReprHash":null,"sourceName":"src/AaveHealthHook.sol","imports":["lib/uniswap-hooks/lib/v4-core/src/interfaces/IExtsload.sol","lib/uniswap-hooks/lib/v4-core/src/interfaces/IExttload.sol","lib/uniswap-hooks/lib/v4-core/src/interfaces/IHooks.sol","lib/uniswap-hooks/lib/v4-core\\src/interfaces/IPoolManager.sol","lib/uniswap-hooks/lib/v4-core/src/interfaces/IProtocolFees.sol","lib/uniswap-hooks/lib/v4-core/src/interfaces/external/IERC20Minimal.sol","lib/uniswap-hooks/lib/v4-core/src/interfaces/external/IERC6909Claims.sol","lib/uniswap-hooks/lib/v4-core/src/libraries/CustomRevert.sol","lib/uniswap-hooks/lib/v4-core\\src/libraries/Hooks.sol","lib/uniswap-hooks/lib/v4-core/src/libraries/LPFeeLibrary.sol","lib/uniswap-hooks/lib/v4-core/src/libraries/ParseBytes.sol","lib/uniswap-hooks/lib/v4-core/src/libraries/SafeCast.sol","lib/uniswap-hooks/lib/v4-core\\src/types/BalanceDelta.sol","lib/uniswap-hooks/lib/v4-core\\src/types/BeforeSwapDelta.sol","lib/uniswap-hooks/lib/v4-core/src/types/Currency.sol","lib/uniswap-hooks/lib/v4-core\\src/types/PoolId.sol","lib/uniswap-hooks/lib/v4-core\\src/types/PoolKey.sol","lib/uniswap-hooks/lib/v4-core/src/types/PoolOperation.sol","lib/uniswap-hooks\\src/base/BaseHook.sol","src\\interfaces\\IAavePool.sol"],"versionRequirement":"^0.8.26","artifacts":{"AaveHealthHook":{"0.8.30":{"default":{"path":"AaveHealthHook.sol\\AaveHealthHook.json","build_id":"c3958264cc353a87"}}}},"seenByCompiler":true},"src/Counter.sol":{"lastModificationDate":1779515454166,"contentHash":"56179e873300c897","interfaceReprHash":null,"sourceName":"src/Counter.sol","imports":["lib/uniswap-hooks/lib/v4-core/src/interfaces/IExtsload.sol","lib/uniswap-hooks/lib/v4-core/src/interfaces/IExttload.sol","lib/uniswap-hooks/lib/v4-core\\src/interfaces/IHooks.sol","lib/uniswap-hooks/lib/v4-core\\src/interfaces/IPoolManager.sol","lib/uniswap-hooks/lib/v4-core/src/interfaces/IProtocolFees.sol","lib/uniswap-hooks/lib/v4-core/src/interfaces/external/IERC20Minimal.sol","lib/uniswap-hooks/lib/v4-core/src/interfaces/external/IERC6909Claims.sol","lib/uniswap-hooks/lib/v4-core/src/libraries/CustomRevert.sol","lib/uniswap-hooks/lib/v4-core\\src/libraries/Hooks.sol","lib/uniswap-hooks/lib/v4-core/src/libraries/LPFeeLibrary.sol","lib/uniswap-hooks/lib/v4-core/src/libraries/ParseBytes.sol","lib/uniswap-hooks/lib/v4-core/src/libraries/SafeCast.sol","lib/uniswap-hooks/lib/v4-core\\src/types/BalanceDelta.sol","lib/uniswap-hooks/lib/v4-core\\src/types/BeforeSwapDelta.sol","lib/uniswap-hooks/lib/v4-core\\src/types/Currency.sol","lib/uniswap-hooks/lib/v4-core\\src/types/PoolId.sol","lib/uniswap-hooks/lib/v4-core\\src/types/PoolKey.sol","lib/uniswap-hooks/lib/v4-core\\src/types/PoolOperation.sol","lib/uniswap-hooks\\src/base/BaseHook.sol"],"versionRequirement":"^0.8.26","artifacts":{"Counter":{"0.8.30":{"default":{"path":"Counter.sol\\Counter.json","build_id":"1d9fdadd1965c4b1"}}}},"seenByCompiler":true},"src/interfaces/IAavePool.sol":{"lastModificationDate":1779515910269,"contentHash":"248aa080e07a9f33","interfaceReprHash":null,"sourceName":"src/interfaces/IAavePool.sol","imports":[],"versionRequirement":"^0.8.24","artifacts":{"IAavePool":{"0.8.30":{"default":{"path":"IAavePool.sol\\IAavePool.json","build_id":"1d9fdadd1965c4b1"}}}},"seenByCompiler":true}},"builds":["036c2ce3fcb75bac","1d5d08d4361a8553","1d9fdadd1965c4b1","a5ea3ad17e6a735e","c3958264cc353a87"],"profiles":{"default":{"solc":{"optimizer":{"enabled":true,"runs":200},"metadata":{"useLiteralContent":false,"bytecodeHash":"none","appendCBOR":true},"outputSelection":{"*":{"*":["abi","evm.bytecode.object","evm.bytecode.sourceMap","evm.bytecode.linkReferences","evm.deployedBytecode.object","evm.deployedBytecode.sourceMap","evm.deployedBytecode.linkReferences","evm.deployedBytecode.immutableReferences","evm.methodIdentifiers","metadata"]}},"evmVersion":"cancun","viaIR":false,"libraries":{}},"vyper":{"evmVersion":"cancun","outputSelection":{"*":{"*":["abi","evm.bytecode","evm.deployedBytecode"]}}}}},"preprocessed":false,"mocks":[]}